qzlt/__init__.py
qzlt/cards.py
qzlt/main.py
qzlt/sessions.py
qzlt/sets.py
qzlt/utils.py
qzlt-0.1.0.dist-info/entry_points.txt
qzlt-0.1.0.dist-info/LICENSE.txt
qzlt-0.1.0.dist-info/WHEEL
qzlt-0.1.0.dist-info/METADATA
qzlt-0.1.0.dist-info/RECORD
