Metadata-Version: 2.1
Name: qzlt
Version: 0.1.0
Summary: A Quizlet clone for the command line
Author: Calvin Cheng
Author-email: calvin.cc.cheng@gmail.com
Requires-Python: >=3.6.2,<4.0.0
Classifier: Programming Language :: Python :: 3
Classifier: Programming Language :: Python :: 3.10
Classifier: Programming Language :: Python :: 3.7
Classifier: Programming Language :: Python :: 3.8
Classifier: Programming Language :: Python :: 3.9
Requires-Dist: typer[all] (>=0.4.1,<0.5.0)
